audio_mask/__init__.py
audio_mask/audio_mask.py
audio_mask-0.0.1.dist-info/LICENSE
audio_mask-0.0.1.dist-info/METADATA
audio_mask-0.0.1.dist-info/WHEEL
audio_mask-0.0.1.dist-info/top_level.txt
audio_mask-0.0.1.dist-info/RECORD
